mg_toolkit/__init__.py
mg_toolkit/__main__.py
mg_toolkit/bulk_download.py
mg_toolkit/constants.py
mg_toolkit/exceptions.py
mg_toolkit/metadata.py
mg_toolkit/search.py
mg_toolkit-0.10.4.dist-info/LICENSE
mg_toolkit-0.10.4.dist-info/METADATA
mg_toolkit-0.10.4.dist-info/WHEEL
mg_toolkit-0.10.4.dist-info/entry_points.txt
mg_toolkit-0.10.4.dist-info/top_level.txt
mg_toolkit-0.10.4.dist-info/RECORD
