Metadata-Version: 2.1
Name: mg-toolkit
Version: 0.10.4
Summary: Metagenomics toolkit.
Home-page: https://github.com/EBI-metagenomics/emg-toolkit
Author: EBI Microbiome Informatics Team
License: Apache Software License
Classifier: Programming Language :: Python :: 3.8
Classifier: Programming Language :: Python :: 3.9
Classifier: Programming Language :: Python :: 3.10
Classifier: Development Status :: 4 - Beta
Classifier: Intended Audience :: Science/Research
Classifier: Topic :: Scientific/Engineering :: Bio-Informatics
Classifier: License :: OSI Approved :: Apache Software License
Classifier: Operating System :: OS Independent
Requires-Python: >=3.8
License-File: LICENSE
Requires-Dist: requests (>=2.31.0)
Requires-Dist: pandas (==2.0.3)
Requires-Dist: jsonapi-client (>=0.9.9)
Requires-Dist: tqdm (>=4.49.0)
Requires-Dist: urllib3 (~=2.2.1)
